setup.py
ucollections.py
pycopy_cpython_ucollections.egg-info/PKG-INFO
pycopy_cpython_ucollections.egg-info/SOURCES.txt
pycopy_cpython_ucollections.egg-info/dependency_links.txt
pycopy_cpython_ucollections.egg-info/top_level.txt